n0struct/__init__.py
n0struct/n0struct_arrays.py
n0struct/n0struct_comprehensions.py
n0struct/n0struct_data_to_json.py
n0struct/n0struct_data_to_xml.py
n0struct/n0struct_data_to_xpath.py
n0struct/n0struct_date.py
n0struct/n0struct_files.py
n0struct/n0struct_files_csv.py
n0struct/n0struct_files_fwf.py
n0struct/n0struct_findall.py
n0struct/n0struct_git.py
n0struct/n0struct_logging.py
n0struct/n0struct_mask.py
n0struct/n0struct_n0compare.py
n0struct/n0struct_n0dict_.py
n0struct/n0struct_n0dict__.py
n0struct/n0struct_n0list_.py
n0struct/n0struct_n0list_n0dict.py
n0struct/n0struct_n0str.py
n0struct/n0struct_n0xml.py
n0struct/n0struct_n1dict_n1list.py
n0struct/n0struct_random.py
n0struct/n0struct_references.py
n0struct/n0struct_transform_dicts.py
n0struct/n0struct_utils.py
n0struct/n0struct_utils_compare.py
n0struct/n0struct_utils_find.py
n0struct/test/__init__.py
n0struct/test/__main__.py
n0struct/test/test_n0struct01.py
n0struct/test/test_n0struct02.py
n0struct/test/test_n0struct03.py
n0struct/test/test_n0struct04.py
n0struct/test/test_n0struct05.py
n0struct/test/test_n0struct06.py
n0struct/test/test_n0struct07.py
n0struct/test/test_n0struct08.py
n0struct/test/test_n0struct09.py
n0struct/test/test_n0struct10.py
n0struct/test/test_n0struct11.py
n0struct/test/test_n0struct12.py
n0struct-0.2.156.dist-info/licenses/LICENSE
n0struct-0.2.156.dist-info/METADATA
n0struct-0.2.156.dist-info/WHEEL
n0struct-0.2.156.dist-info/top_level.txt
n0struct-0.2.156.dist-info/RECORD
